[
  {
    "title": "First Event",
    "description": "This is the description of the first event.",
    "public": true
  },
  {
    "title": "Second Event",
    "description": "Another event with a description.",
    "public": false
  },
  {
    "title": "Third Event",
    "description": "Description for the third event.",
    "public": true
  },
  {
    "title": "Fourth Event",
    "description": null,
    "public": false
  },
  {
    "title": "Fifth Event",
    "description": "Description for the fifth event.",
    "public": true
  },
  {
    "title": "Sixth Event",
    "description": "Another event with a description.",
    "public": false
  }
]

